aitrados_api/__init__.py
aitrados_api/api_lib/common_request.py
aitrados_api/api_lib/economic_request.py
aitrados_api/api_lib/holiday_request.py
aitrados_api/api_lib/news_request.py
aitrados_api/api_lib/ohlc_request.py
aitrados_api/api_lib/other_request.py
aitrados_api/api_lib/reference_request.py
aitrados_api/api_lib/request_base_mixin.py
aitrados_api/common_lib/any_list_data_to_format_data.py
aitrados_api/common_lib/common.py
aitrados_api/common_lib/common_remote_curl.py
aitrados_api/common_lib/contant.py
aitrados_api/common_lib/exceptions.py
aitrados_api/common_lib/response_format.py
aitrados_api/common_lib/run_utils.py
aitrados_api/common_lib/utils.py
aitrados_api/common_lib/http_api/base.py
aitrados_api/common_lib/http_api/config.py
aitrados_api/common_lib/http_api/data_client.py
aitrados_api/common_lib/http_api/rate_limit.py
aitrados_api/common_lib/subscribe_api/websocks_client.py
aitrados_api/common_lib/tools/toml_manager.py
aitrados_api/latest_ohlc_chart_flow/latest_ohlc_chart_flow.py
aitrados_api/latest_ohlc_chart_flow/latest_ohlc_chart_flow_manager.py
aitrados_api/latest_ohlc_chart_flow/ohlc_aggregation/ohlc_aggregation_minute.py
aitrados_api/latest_ohlc_chart_flow/ohlc_aggregation/ohlc_aggregation_utils.py
aitrados_api/latest_ohlc_multi_timeframe_alignment_flow/latest_ohlc_multi_timeframe_alignment.py
aitrados_api/latest_ohlc_multi_timeframe_alignment_flow/latest_ohlc_multi_timeframe_manager.py
aitrados_api/latest_ohlc_multi_timeframe_alignment_flow/unique_name_generator.py
aitrados_api/models/base_model.py
aitrados_api/models/economic_model.py
aitrados_api/models/holiday_model.py
aitrados_api/models/news_model.py
aitrados_api/models/ohlc_model.py
aitrados_api/models/other_model.py
aitrados_api/models/reference_model.py
aitrados_api/trade_middleware/__init__.py
aitrados_api/trade_middleware/async_pubsub_intelligent_router.py
aitrados_api/trade_middleware/async_rpc_intelligent_router.py
aitrados_api/trade_middleware/backend_service.py
aitrados_api-0.2.0.dist-info/METADATA
aitrados_api-0.2.0.dist-info/WHEEL
aitrados_api-0.2.0.dist-info/licenses/LICENSE
aitrados_api-0.2.0.dist-info/RECORD
