Metadata-Version: 2.4
Name: aitrados-api
Version: 0.2.0
Summary: A  client library for the Aitrados data platform, providing access to real-time and historical financial market data via HTTP and WebSocket APIs.specifically designed for AI quantitative trading/training.Multiple Timeframes,Multiple-Symbols-Multiple-Timeframes Alignment
Project-URL: Homepage, https://github.com/aitrados/aitrados-api
Project-URL: Bug Tracker, https://github.com/aitrados/aitrados-api/issues
Project-URL: Repository, https://github.com/aitrados/aitrados-api
Project-URL: Documentation, https://github.com/aitrados/aitrados-api
Author-email: Alexander <support@aitrados.com>
License: MIT License
License-File: LICENSE
Keywords: AI,api,data,finance streaming,financial,market-data,ohlc,ohlcv,quantitative,real-time,streaming ohlc,trading,websockes ohlc,ws ohlc
Classifier: Environment :: Console
Classifier: Environment :: Web Environment
Classifier: Intended Audience :: Developers
Classifier: Intended Audience :: Financial and Insurance Industry
Classifier: License :: OSI Approved :: MIT License
Classifier: Operating System :: OS Independent
Classifier: Programming Language :: Python :: 3
Classifier: Programming Language :: Python :: 3.10
Classifier: Programming Language :: Python :: 3.11
Classifier: Programming Language :: Python :: 3.12
Classifier: Programming Language :: Python :: 3.13
Classifier: Programming Language :: Python :: 3.14
Classifier: Topic :: Office/Business :: Financial
Classifier: Topic :: Office/Business :: Financial :: Investment
Classifier: Topic :: Scientific/Engineering :: Information Analysis
Classifier: Topic :: Software Development :: Libraries :: Python Modules
Requires-Python: >=3.10
Requires-Dist: aiofiles
Requires-Dist: httpx
Requires-Dist: loguru
Requires-Dist: pandas
Requires-Dist: polars
Requires-Dist: pyarrow
Requires-Dist: pydantic
Requires-Dist: python-dotenv
Requires-Dist: pyzmq
Requires-Dist: tenacity
Requires-Dist: tornado>=6.5.2
Requires-Dist: websockets
